{
  "FormKey": "000016:TintsOfASuccubusSecretDesires.esp",
  "EditorID": "TSSD_Drain_GentleDrain3",
  "Name": {
    "TargetLanguage": "English",
    "Value": "Gentle Drain"
  },
  "Description": {
    "TargetLanguage": "English",
    "Value": "You learn to limit your drain somewhat. Friendly targets can be drained again after only a quarter of the time and the debuff is no longer as debilitating."
  },
  "Conditions": [
    {
      "MutagenObjectType": "ConditionFloat",
      "CompareOperator": "GreaterThanOrEqualTo",
      "Data": {
        "MutagenObjectType": "GetGlobalValueConditionData",
        "Global": "000002:TintsOfASuccubusSecretDesires.esp"
      },
      "ComparisonValue": 60.0
    }
  ],
  "NumRanks": 1,
  "Playable": true,
  "NextPerk": "000017:TintsOfASuccubusSecretDesires.esp"
}