{
  "FormKey": "000082:TintsOfASuccubusSecretDesires.esp",
  "EditorID": "tssd_perkscripts",
  "VirtualMachineAdapter": {
    "Scripts": [
      {
        "Name": "QF_tssd_perkscripts_08000082",
        "Properties": [
          {
            "MutagenObjectType": "ScriptObjectProperty",
            "Name": "TSSD_Base_TraitGain",
            "Object": "000029:TintsOfASuccubusSecretDesires.esp"
          },
          {
            "MutagenObjectType": "ScriptObjectProperty",
            "Name": "TSSD_MaxTraits",
            "Object": "000034:TintsOfASuccubusSecretDesires.esp"
          },
          {
            "MutagenObjectType": "ScriptObjectProperty",
            "Name": "TSSD_FilledUpBuffs",
            "Object": "000083:TintsOfASuccubusSecretDesires.esp"
          },
          {
            "MutagenObjectType": "ScriptObjectProperty",
            "Name": "Alias_PlayerRef",
            "Object": "000082:TintsOfASuccubusSecretDesires.esp",
            "Alias": 0
          }
        ]
      }
    ],
    "FileName": "QF_tssd_perkscripts_08000082",
    "Fragments": [
      {
        "Stage": 2,
        "Unknown2": 1,
        "ScriptName": "QF_tssd_perkscripts_08000082",
        "FragmentName": "Fragment_2"
      },
      {
        "Stage": 1,
        "Unknown2": 1,
        "ScriptName": "QF_tssd_perkscripts_08000082",
        "FragmentName": "Fragment_0"
      }
    ]
  },
  "Flags": [
    "AllowRepeatedStages"
  ],
  "Stages": [
    {},
    {
      "Index": 1,
      "LogEntries": [
        {
          "Flags": []
        }
      ]
    },
    {
      "Index": 2,
      "LogEntries": [
        {
          "Flags": []
        }
      ]
    },
    {
      "Index": 3,
      "LogEntries": [
        {
          "Flags": []
        }
      ]
    }
  ],
  "NextAliasID": 1,
  "Aliases": [
    {
      "Name": "PlayerRef",
      "Flags": [],
      "ForcedReference": "000014:Skyrim.esm",
      "VoiceTypes": "Null"
    }
  ]
}