{
  "FormKey": "00001A:TintsOfASuccubusSecretDesires.esp",
  "EditorID": "TSSD_ClawMultiplier",
  "Name": {
    "TargetLanguage": "English",
    "Value": "Long Nails"
  },
  "Flags": [
    "NoDuration",
    "NoArea",
    "NoRecast",
    "Painless",
    "NoHitEffect"
  ],
  "Archetype": {
    "MutagenObjectType": "MagicEffectPeakValueModArchetype",
    "ActorValue": "UnarmedDamage"
  },
  "DualCastScale": 1.0,
  "CastingSoundLevel": "Normal",
  "Sounds": [],
  "Description": {
    "TargetLanguage": "English",
    "Value": "Your claw-like nails deal <mag> more damage."
  }
}